sage/middleware/__init__.py
sage/middleware/_version.py
sage/middleware/py.typed
sage/middleware/components/__init__.py
sage/middleware/components/extensions_compat.py
sage/middleware/components/sage_db/__init__.py
sage/middleware/components/sage_db/backend.py
sage/middleware/components/sage_db/service.py
sage/middleware/components/sage_flow/__init__.py
sage/middleware/components/sage_flow/service.py
sage/middleware/components/sage_flow/python/__init__.py
sage/middleware/components/sage_flow/python/sage_flow.py
sage/middleware/components/sage_flow/python/micro_service/__init__.py
sage/middleware/components/sage_flow/python/micro_service/sage_flow_service.py
sage/middleware/components/sage_mem/__init__.py
sage/middleware/components/sage_sias/__init__.py
sage/middleware/components/sage_sias/continual_learner.py
sage/middleware/components/sage_sias/coreset_selector.py
sage/middleware/components/sage_sias/types.py
sage/middleware/components/sage_tsdb/__init__.py
sage/middleware/components/sage_tsdb/service.py
sage/middleware/components/sage_tsdb/python/__init__.py
sage/middleware/components/sage_tsdb/python/_sage_tsdb.pyi
sage/middleware/components/sage_tsdb/python/sage_tsdb.py
sage/middleware/components/sage_tsdb/python/algorithms/__init__.py
sage/middleware/components/sage_tsdb/python/algorithms/base.py
sage/middleware/components/sage_tsdb/python/algorithms/out_of_order_join.py
sage/middleware/components/sage_tsdb/python/algorithms/window_aggregator.py
sage/middleware/components/sage_tsdb/python/micro_service/__init__.py
sage/middleware/components/sage_tsdb/python/micro_service/sage_tsdb_service.py
sage/middleware/components/vector_stores/__init__.py
sage/middleware/components/vector_stores/chroma.py
sage/middleware/components/vector_stores/chroma_adapter.py
sage/middleware/components/vector_stores/milvus.py
sage/middleware/operators/__init__.py
sage/middleware/operators/agent/__init__.py
sage/middleware/operators/agent/runtime.py
isage_middleware-0.2.4.3.dist-info/METADATA
isage_middleware-0.2.4.3.dist-info/WHEEL
isage_middleware-0.2.4.3.dist-info/top_level.txt
isage_middleware-0.2.4.3.dist-info/RECORD
