Metadata-Version: 2.1
Name: isage-middleware
Version: 0.2.4.3
Summary: SAGE Middleware - Streaming-Augmented Generative Execution
Author-email: IntelliStream Team <shuhao_zhang@hust.edu.cn>
License: MIT
Project-URL: Homepage, https://github.com/intellistream/SAGE
Project-URL: Repository, https://github.com/intellistream/SAGE.git
Project-URL: Documentation, https://intellistream.github.io/SAGE-Pub/
Project-URL: Issues, https://github.com/intellistream/SAGE/issues
Keywords: data,api,reasoning,dataflow,llm,ml,middleware,framework,rag,intellistream,ai,sage
Classifier: Development Status :: 4 - Beta
Classifier: Intended Audience :: Developers
Classifier: Intended Audience :: Science/Research
Classifier: Operating System :: OS Independent
Classifier: Topic :: Scientific/Engineering :: Artificial Intelligence
Classifier: Topic :: Software Development :: Libraries :: Python Modules
Classifier: Topic :: System :: Distributed Computing
Requires-Python: >=3.10
Requires-Dist: openai<1.91.0,>=1.52.0
Requires-Dist: httpx<1.0.0,>=0.28.0
Requires-Dist: aiohttp<4.0.0,>=3.12.0
Requires-Dist: beautifulsoup4<5.0.0,>=4.12.0
Requires-Dist: feedparser<7.0.0,>=6.0.11
Requires-Dist: json-repair<1.0.0,>=0.30.0
Requires-Dist: bm25s<1.0.0,>=0.2.13
Requires-Dist: rank-bm25<1.0.0,>=0.2.0
Requires-Dist: PyStemmer<4.0.0,>=3.0.0
Provides-Extra: all
Requires-Dist: isage-middleware[auth,compression,libs,llm-providers,ml,neuromem,queue,streaming,vdb]; extra == "all"
Provides-Extra: auth
Requires-Dist: python-jose[cryptography]<4.0.0,>=3.5.0; extra == "auth"
Requires-Dist: passlib[argon2]<2.0.0,>=1.7.4; extra == "auth"
Provides-Extra: compression
Requires-Dist: llmlingua<1.0.0,>=0.2.0; extra == "compression"
Provides-Extra: dev
Requires-Dist: pytest>=7.4.0; extra == "dev"
Requires-Dist: pytest-cov>=4.0.0; extra == "dev"
Requires-Dist: pytest-asyncio>=0.21.0; extra == "dev"
Requires-Dist: ruff==0.14.6; extra == "dev"
Requires-Dist: mypy>=1.7.0; extra == "dev"
Requires-Dist: pybind11>=2.10.0; extra == "dev"
Provides-Extra: libs
Requires-Dist: isage-libs; extra == "libs"
Requires-Dist: isage-agentic>=0.1.0.0; extra == "libs"
Requires-Dist: isage-eval>=0.1.0.0; extra == "libs"
Requires-Dist: isage-finetune>=0.1.0.0; extra == "libs"
Requires-Dist: isage-privacy>=0.1.0.0; extra == "libs"
Requires-Dist: isage-rag>=0.1.0.0; extra == "libs"
Requires-Dist: isage-safety>=0.1.0.0; extra == "libs"
Requires-Dist: isage-refiner>=0.1.0.0; extra == "libs"
Provides-Extra: llm-providers
Requires-Dist: ollama<1.0.0,>=0.5.0; extra == "llm-providers"
Requires-Dist: zhipuai<3.0.0,>=2.1.0; extra == "llm-providers"
Requires-Dist: cohere<6.0.0,>=5.16.0; extra == "llm-providers"
Requires-Dist: anthropic<1.0.0,>=0.25.0; extra == "llm-providers"
Provides-Extra: ml
Requires-Dist: transformers<4.54.0,>=4.52.0; extra == "ml"
Requires-Dist: tokenizers<0.24.0,>=0.21.0; extra == "ml"
Requires-Dist: sentence-transformers<4.0.0,>=3.1.0; extra == "ml"
Requires-Dist: InstructorEmbedding<2.0.0,>=1.0.0; extra == "ml"
Requires-Dist: accelerate<2.0.0,>=1.9.0; extra == "ml"
Requires-Dist: huggingface-hub<1.0.0,>=0.34.0; extra == "ml"
Requires-Dist: peft<1.0.0,>=0.18.0; extra == "ml"
Requires-Dist: scipy<2.0.0,>=1.15.0; extra == "ml"
Provides-Extra: neuromem
Requires-Dist: isage-neuromem>=0.2.1.1; extra == "neuromem"
Provides-Extra: queue
Requires-Dist: celery<6.0.0,>=5.5.0; extra == "queue"
Requires-Dist: flower<3.0.0,>=2.0.0; extra == "queue"
Provides-Extra: streaming
Requires-Dist: isage-flow>=0.1.1; extra == "streaming"
Requires-Dist: isage-tsdb>=0.1.5; extra == "streaming"
Provides-Extra: vdb
Requires-Dist: isage-vdb>=0.1.5; extra == "vdb"
Requires-Dist: faiss-cpu<2.0.0,>=1.7.0; extra == "vdb"
